RutishauserLabtoNWB/__init__.py
RutishauserLabtoNWB/3rdParty/matnwb/.gitignore
RutishauserLabtoNWB/3rdParty/matnwb/CODE_OF_CONDUCT.md
RutishauserLabtoNWB/3rdParty/matnwb/LICENSE
RutishauserLabtoNWB/3rdParty/matnwb/NwbFile.m
RutishauserLabtoNWB/3rdParty/matnwb/README.md
RutishauserLabtoNWB/3rdParty/matnwb/functionSignatures.json
RutishauserLabtoNWB/3rdParty/matnwb/generateCore.m
RutishauserLabtoNWB/3rdParty/matnwb/generateExtension.m
RutishauserLabtoNWB/3rdParty/matnwb/nwbExport.m
RutishauserLabtoNWB/3rdParty/matnwb/nwbRead.m
RutishauserLabtoNWB/3rdParty/matnwb/nwbtest.m
RutishauserLabtoNWB/3rdParty/matnwb/+contrib/+blackrock/AddNEVFile.m
RutishauserLabtoNWB/3rdParty/matnwb/+contrib/+blackrock/AddNSFile.m
RutishauserLabtoNWB/3rdParty/matnwb/+contrib/+blackrock/README.md
RutishauserLabtoNWB/3rdParty/matnwb/+contrib/+blackrock/get_channel_info.m
RutishauserLabtoNWB/3rdParty/matnwb/+contrib/+mworks/AddEyePos.m
RutishauserLabtoNWB/3rdParty/matnwb/+contrib/+mworks/README.md
RutishauserLabtoNWB/3rdParty/matnwb/+contrib/+tdt/README.md
RutishauserLabtoNWB/3rdParty/matnwb/+contrib/+tdt/TDT2NWB.m
RutishauserLabtoNWB/3rdParty/matnwb/+contrib/+tdt/TDTbin2mat.m
RutishauserLabtoNWB/3rdParty/matnwb/+contrib/+tdt/addECoG.m
RutishauserLabtoNWB/3rdParty/matnwb/+contrib/+tdt/addElectrodeTable.m
RutishauserLabtoNWB/3rdParty/matnwb/+file/Attribute.m
RutishauserLabtoNWB/3rdParty/matnwb/+file/Dataset.m
RutishauserLabtoNWB/3rdParty/matnwb/+file/Group.m
RutishauserLabtoNWB/3rdParty/matnwb/+file/Link.m
RutishauserLabtoNWB/3rdParty/matnwb/+file/addSpaces.m
RutishauserLabtoNWB/3rdParty/matnwb/+file/fillClass.m
RutishauserLabtoNWB/3rdParty/matnwb/+file/fillConstructor.m
RutishauserLabtoNWB/3rdParty/matnwb/+file/fillExport.m
RutishauserLabtoNWB/3rdParty/matnwb/+file/fillProps.m
RutishauserLabtoNWB/3rdParty/matnwb/+file/fillSetters.m
RutishauserLabtoNWB/3rdParty/matnwb/+file/fillValidators.m
RutishauserLabtoNWB/3rdParty/matnwb/+file/mapType.m
RutishauserLabtoNWB/3rdParty/matnwb/+file/procdims.m
RutishauserLabtoNWB-1.0.2.dist-info/LICENSE.txt
RutishauserLabtoNWB-1.0.2.dist-info/METADATA
RutishauserLabtoNWB-1.0.2.dist-info/WHEEL
RutishauserLabtoNWB-1.0.2.dist-info/top_level.txt
RutishauserLabtoNWB-1.0.2.dist-info/RECORD
