Metadata-Version: 2.1
Name: RutishauserLabtoNWB
Version: 1.0.2
Summary: Export and Analysis Code for NWB:N
Home-page: https://github.com/rutishauserlab/recogmem-release-NWB
Author: Nand Chandravadia
Author-email: nand.chandravadia@cshs.org
License: BSD
Keywords: Cognitive Neuroscience,Neuroscience,Neurosurgery,Single Unit Recordings,Data Standardization
Platform: UNKNOWN
Classifier: Programming Language :: Python :: 3
Classifier: Operating System :: OS Independent
Requires-Python: >=3.0
Requires-Dist: numpy
Requires-Dist: pandas
Requires-Dist: scipy
Requires-Dist: matplotlib
Requires-Dist: pynwb
Requires-Dist: opencv-python
